manim_physics/__init__.py
manim_physics/electromagnetism/__init__.py
manim_physics/electromagnetism/electrostatics.py
manim_physics/electromagnetism/magnetostatics.py
manim_physics/optics/__init__.py
manim_physics/optics/lenses.py
manim_physics/optics/rays.py
manim_physics/rigid_mechanics/__init__.py
manim_physics/rigid_mechanics/pendulum.py
manim_physics/rigid_mechanics/rigid_mechanics.py
manim_physics/wave.py
manim_physics-0.3.0.dist-info/entry_points.txt
manim_physics-0.3.0.dist-info/METADATA
manim_physics-0.3.0.dist-info/WHEEL
manim_physics-0.3.0.dist-info/RECORD
