Metadata-Version: 2.1
Name: manim-physics
Version: 0.3.0
Summary: Support physics simulation
Home-page: https://github.com/Matheart/manim-physics
Author: Matheart
Author-email: waautomationwong@gmail.com
Requires-Python: >=3.8,<3.12
Classifier: Programming Language :: Python :: 3
Classifier: Programming Language :: Python :: 3.8
Classifier: Programming Language :: Python :: 3.9
Classifier: Programming Language :: Python :: 3.10
Classifier: Programming Language :: Python :: 3.11
Requires-Dist: Shapely (>=1.8.0,<2.0.0)
Requires-Dist: manim (>=0.17.3,<0.18.0)
Requires-Dist: pymunk (>=6.0.0,<7.0.0)
Project-URL: Repository, https://github.com/Matheart/manim-physics
